{"name":"View detail offline classes","id":"manage-offline-class;view-detail-offline-classes","testSteps":[{"number":1,"description":"1: View detail offline classes ({row\u003d1, crud_button\u003dview})","duration":7699,"startTime":"2022-07-01T20:11:35.350164400+07:00[Asia/Bangkok]","screenshots":[{"screenshot":"9a3ea4ae46d5435bcc72df02a071db11a36c5d15aafb9967d2491896b8eb1e73.png","timeStamp":1656681103049}],"result":"SUCCESS","precondition":false,"level":0,"lineNumber":12,"children":[{"number":2,"description":"Given I am on manage offline class menu","duration":6276,"startTime":"2022-07-01T20:11:35.352159500+07:00[Asia/Bangkok]","screenshots":[{"screenshot":"0f3a75a0745c80e828e86b7f62df24919d621cf99b4b5a14dd04acbe000f5cdc.png","timeStamp":1656681101628}],"result":"SUCCESS","precondition":false,"level":1,"children":[{"number":3,"description":"Maximise screen","duration":715,"startTime":"2022-07-01T20:11:39.682717900+07:00[Asia/Bangkok]","screenshots":[{"screenshot":"2dbf94df25107e0631ffc5093e7daa00153e52ff7f4e7535e7c5e0184d600708.png","timeStamp":1656681100038},{"screenshot":"68986ae304f885f6575cb791394cc4e388b6e51ca3c62bc457dd7c48e0147f48.png","timeStamp":1656681100398}],"result":"SUCCESS","precondition":false,"level":2},{"number":4,"description":"Click manage offline class","duration":912,"startTime":"2022-07-01T20:11:40.401094+07:00[Asia/Bangkok]","screenshots":[{"screenshot":"68986ae304f885f6575cb791394cc4e388b6e51ca3c62bc457dd7c48e0147f48.png","timeStamp":1656681100406},{"screenshot":"0f3a75a0745c80e828e86b7f62df24919d621cf99b4b5a14dd04acbe000f5cdc.png","timeStamp":1656681101313}],"result":"SUCCESS","precondition":false,"level":2},{"number":5,"description":"Validate on manage offline class menu","duration":307,"startTime":"2022-07-01T20:11:41.316822200+07:00[Asia/Bangkok]","screenshots":[{"screenshot":"0f3a75a0745c80e828e86b7f62df24919d621cf99b4b5a14dd04acbe000f5cdc.png","timeStamp":1656681101321},{"screenshot":"0f3a75a0745c80e828e86b7f62df24919d621cf99b4b5a14dd04acbe000f5cdc.png","timeStamp":1656681101623}],"result":"SUCCESS","precondition":false,"level":2}]},{"number":6,"description":"When I click button on offline class 1 \"view\"","duration":861,"startTime":"2022-07-01T20:11:41.629850900+07:00[Asia/Bangkok]","screenshots":[{"screenshot":"0f3a75a0745c80e828e86b7f62df24919d621cf99b4b5a14dd04acbe000f5cdc.png","timeStamp":1656681101635},{"screenshot":"ac84a0a261bbd35eea2cf08c6d902a8827e7e934c30b32f4f511e5002d3a6468.png","timeStamp":1656681102490}],"result":"SUCCESS","precondition":false,"level":1,"children":[{"number":7,"description":"Click CRU dbutton: view, 1","duration":844,"startTime":"2022-07-01T20:11:41.639824800+07:00[Asia/Bangkok]","screenshots":[{"screenshot":"0f3a75a0745c80e828e86b7f62df24919d621cf99b4b5a14dd04acbe000f5cdc.png","timeStamp":1656681101645},{"screenshot":"ac84a0a261bbd35eea2cf08c6d902a8827e7e934c30b32f4f511e5002d3a6468.png","timeStamp":1656681102483}],"result":"SUCCESS","precondition":false,"level":2}]},{"number":8,"description":"Then I validate the popup view offline class will show","duration":544,"startTime":"2022-07-01T20:11:42.498980+07:00[Asia/Bangkok]","screenshots":[{"screenshot":"ac84a0a261bbd35eea2cf08c6d902a8827e7e934c30b32f4f511e5002d3a6468.png","timeStamp":1656681102504},{"screenshot":"9a3ea4ae46d5435bcc72df02a071db11a36c5d15aafb9967d2491896b8eb1e73.png","timeStamp":1656681103043}],"result":"SUCCESS","precondition":false,"level":1,"children":[{"number":9,"description":"View offline class pop up show","duration":507,"startTime":"2022-07-01T20:11:42.507915300+07:00[Asia/Bangkok]","screenshots":[{"screenshot":"ac84a0a261bbd35eea2cf08c6d902a8827e7e934c30b32f4f511e5002d3a6468.png","timeStamp":1656681102514},{"screenshot":"9a3ea4ae46d5435bcc72df02a071db11a36c5d15aafb9967d2491896b8eb1e73.png","timeStamp":1656681103015}],"result":"SUCCESS","precondition":false,"level":2}]}]},{"number":10,"description":"2: View detail offline classes ({row\u003d2, crud_button\u003dview})","duration":6888,"startTime":"2022-07-01T20:11:44.648176200+07:00[Asia/Bangkok]","screenshots":[{"screenshot":"3f6a4e101f527bf35c1dd06eca4405c921aae8865206aa0d5a8c10d44b2d5674.png","timeStamp":1656681111536}],"result":"SUCCESS","precondition":false,"level":0,"lineNumber":13,"children":[{"number":11,"description":"Given I am on manage offline class menu","duration":5842,"startTime":"2022-07-01T20:11:44.650186400+07:00[Asia/Bangkok]","screenshots":[{"screenshot":"0f3a75a0745c80e828e86b7f62df24919d621cf99b4b5a14dd04acbe000f5cdc.png","timeStamp":1656681110492}],"result":"SUCCESS","precondition":false,"level":1,"children":[{"number":12,"description":"Maximise screen","duration":652,"startTime":"2022-07-01T20:11:48.967150800+07:00[Asia/Bangkok]","screenshots":[{"screenshot":"2dbf94df25107e0631ffc5093e7daa00153e52ff7f4e7535e7c5e0184d600708.png","timeStamp":1656681109262},{"screenshot":"68986ae304f885f6575cb791394cc4e388b6e51ca3c62bc457dd7c48e0147f48.png","timeStamp":1656681109619}],"result":"SUCCESS","precondition":false,"level":2},{"number":13,"description":"Click manage offline class","duration":612,"startTime":"2022-07-01T20:11:49.621951900+07:00[Asia/Bangkok]","screenshots":[{"screenshot":"68986ae304f885f6575cb791394cc4e388b6e51ca3c62bc457dd7c48e0147f48.png","timeStamp":1656681109626},{"screenshot":"0f3a75a0745c80e828e86b7f62df24919d621cf99b4b5a14dd04acbe000f5cdc.png","timeStamp":1656681110234}],"result":"SUCCESS","precondition":false,"level":2},{"number":14,"description":"Validate on manage offline class menu","duration":44,"startTime":"2022-07-01T20:11:50.236152400+07:00[Asia/Bangkok]","screenshots":[{"screenshot":"0f3a75a0745c80e828e86b7f62df24919d621cf99b4b5a14dd04acbe000f5cdc.png","timeStamp":1656681110240},{"screenshot":"0f3a75a0745c80e828e86b7f62df24919d621cf99b4b5a14dd04acbe000f5cdc.png","timeStamp":1656681110280}],"result":"SUCCESS","precondition":false,"level":2}]},{"number":15,"description":"When I click button on offline class 2 \"view\"","duration":656,"startTime":"2022-07-01T20:11:50.493742400+07:00[Asia/Bangkok]","screenshots":[{"screenshot":"0f3a75a0745c80e828e86b7f62df24919d621cf99b4b5a14dd04acbe000f5cdc.png","timeStamp":1656681110497},{"screenshot":"d3272cc85585e5bcad4eee370aede4770b73d1000ca6ea3329590f1da13abcc1.png","timeStamp":1656681111150}],"result":"SUCCESS","precondition":false,"level":1,"children":[{"number":16,"description":"Click CRU dbutton: view, 2","duration":646,"startTime":"2022-07-01T20:11:50.499208600+07:00[Asia/Bangkok]","screenshots":[{"screenshot":"0f3a75a0745c80e828e86b7f62df24919d621cf99b4b5a14dd04acbe000f5cdc.png","timeStamp":1656681110503},{"screenshot":"d3272cc85585e5bcad4eee370aede4770b73d1000ca6ea3329590f1da13abcc1.png","timeStamp":1656681111146}],"result":"SUCCESS","precondition":false,"level":2}]},{"number":17,"description":"Then I validate the popup view offline class will show","duration":381,"startTime":"2022-07-01T20:11:51.151080900+07:00[Asia/Bangkok]","screenshots":[{"screenshot":"d3272cc85585e5bcad4eee370aede4770b73d1000ca6ea3329590f1da13abcc1.png","timeStamp":1656681111156},{"screenshot":"3f6a4e101f527bf35c1dd06eca4405c921aae8865206aa0d5a8c10d44b2d5674.png","timeStamp":1656681111532}],"result":"SUCCESS","precondition":false,"level":1,"children":[{"number":18,"description":"View offline class pop up show","duration":371,"startTime":"2022-07-01T20:11:51.157094500+07:00[Asia/Bangkok]","screenshots":[{"screenshot":"d3272cc85585e5bcad4eee370aede4770b73d1000ca6ea3329590f1da13abcc1.png","timeStamp":1656681111161},{"screenshot":"3f6a4e101f527bf35c1dd06eca4405c921aae8865206aa0d5a8c10d44b2d5674.png","timeStamp":1656681111528}],"result":"SUCCESS","precondition":false,"level":2}]}]}],"userStory":{"id":"manage-offline-class","storyName":"Manage Offline Class","displayName":"Manage Offline Class","path":"ManageOfflineClass.feature","narrative":"  As an Admin\n  I want to manage data offline classes\n  So that I can do some CRUD in manage offline class menu","type":"feature"},"featureTag":{"name":"Manage Offline Class","type":"feature","displayName":"Manage Offline Class"},"title":"View detail offline classes","description":"","tags":[{"name":"Manage Offline Class","type":"feature","displayName":"Manage Offline Class"}],"startTime":"2022-07-01T20:11:35.343183+07:00[Asia/Bangkok]","duration":16878,"projectKey":"","driver":"chrome","isManualTestingUpToDate":false,"dataTable":{"headers":["row","crud_button"],"rows":[{"values":["1","view"],"lineNumber":12,"result":"SUCCESS"},{"values":["2","view"],"lineNumber":13,"result":"SUCCESS"}],"predefinedRows":true,"scenarioOutline":"Given I am on manage offline class menu\n\rWhen I click button on offline class \u003crow\u003e \"\u003ccrud_button\u003e\"\n\rThen I validate the popup view offline class will show\n\r","dataSetDescriptors":[{"startRow":0,"rowCount":0,"name":"","description":""}]},"manual":false,"testSource":"Cucumber","result":"SUCCESS","scenarioOutline":"Given I am on manage offline class menu\r\nWhen I click button on offline class \u003crow\u003e \"\u003ccrud_button\u003e\"\r\nThen I validate the popup view offline class will show"}